[{"CourseID":1,"Title":"Accounting","Credits":4},
{"CourseID":2,"Title":"Sales","Credits":3},
{"CourseID":3,"Title":"Legal","Credits":5},
{"CourseID":4,"Title":"Human Resources","Credits":5},
{"CourseID":5,"Title":"Product Management","Credits":2},
{"CourseID":6,"Title":"Research and Development","Credits":1},
{"CourseID":7,"Title":"Marketing","Credits":3},
{"CourseID":8,"Title":"Product Management","Credits":1},
{"CourseID":9,"Title":"Accounting","Credits":4},
{"CourseID":10,"Title":"Human Resources","Credits":3},
{"CourseID":11,"Title":"Product Management","Credits":1},
{"CourseID":12,"Title":"Business Development","Credits":1},
{"CourseID":13,"Title":"Engineering","Credits":2},
{"CourseID":14,"Title":"Support","Credits":4},
{"CourseID":15,"Title":"Services","Credits":4},
{"CourseID":16,"Title":"Product Management","Credits":5},
{"CourseID":17,"Title":"Product Management","Credits":1},
{"CourseID":18,"Title":"Business Development","Credits":1},
{"CourseID":19,"Title":"Product Management","Credits":5},
{"CourseID":20,"Title":"Support","Credits":2},
{"CourseID":21,"Title":"Human Resources","Credits":5},
{"CourseID":22,"Title":"Marketing","Credits":5},
{"CourseID":23,"Title":"Sales","Credits":3},
{"CourseID":24,"Title":"Services","Credits":5},
{"CourseID":25,"Title":"Services","Credits":2},
{"CourseID":26,"Title":"Sales","Credits":4},
{"CourseID":27,"Title":"Accounting","Credits":2},
{"CourseID":28,"Title":"Legal","Credits":3},
{"CourseID":29,"Title":"Training","Credits":5},
{"CourseID":30,"Title":"Product Management","Credits":1},
{"CourseID":31,"Title":"Support","Credits":2},
{"CourseID":32,"Title":"Marketing","Credits":2},
{"CourseID":33,"Title":"Research and Development","Credits":2},
{"CourseID":34,"Title":"Product Management","Credits":4},
{"CourseID":35,"Title":"Sales","Credits":5},
{"CourseID":36,"Title":"Engineering","Credits":3},
{"CourseID":37,"Title":"Training","Credits":2},
{"CourseID":38,"Title":"Marketing","Credits":1},
{"CourseID":39,"Title":"Research and Development","Credits":5},
{"CourseID":40,"Title":"Engineering","Credits":3},
{"CourseID":41,"Title":"Engineering","Credits":2},
{"CourseID":42,"Title":"Legal","Credits":4},
{"CourseID":43,"Title":"Research and Development","Credits":4},
{"CourseID":44,"Title":"Training","Credits":4},
{"CourseID":45,"Title":"Support","Credits":2},
{"CourseID":46,"Title":"Support","Credits":3},
{"CourseID":47,"Title":"Engineering","Credits":5},
{"CourseID":48,"Title":"Product Management","Credits":4},
{"CourseID":49,"Title":"Training","Credits":3},
{"CourseID":50,"Title":"Engineering","Credits":1},
{"CourseID":51,"Title":"Marketing","Credits":4},
{"CourseID":52,"Title":"Sales","Credits":4},
{"CourseID":53,"Title":"Sales","Credits":1},
{"CourseID":54,"Title":"Business Development","Credits":5},
{"CourseID":55,"Title":"Services","Credits":4},
{"CourseID":56,"Title":"Training","Credits":4},
{"CourseID":57,"Title":"Human Resources","Credits":4},
{"CourseID":58,"Title":"Services","Credits":4},
{"CourseID":59,"Title":"Business Development","Credits":4},
{"CourseID":60,"Title":"Training","Credits":1},
{"CourseID":61,"Title":"Engineering","Credits":4},
{"CourseID":62,"Title":"Accounting","Credits":4},
{"CourseID":63,"Title":"Research and Development","Credits":4},
{"CourseID":64,"Title":"Business Development","Credits":5},
{"CourseID":65,"Title":"Legal","Credits":1},
{"CourseID":66,"Title":"Support","Credits":2},
{"CourseID":67,"Title":"Sales","Credits":3},
{"CourseID":68,"Title":"Support","Credits":2},
{"CourseID":69,"Title":"Engineering","Credits":5},
{"CourseID":70,"Title":"Legal","Credits":2},
{"CourseID":71,"Title":"Services","Credits":5},
{"CourseID":72,"Title":"Research and Development","Credits":4},
{"CourseID":73,"Title":"Support","Credits":1},
{"CourseID":74,"Title":"Human Resources","Credits":1},
{"CourseID":75,"Title":"Training","Credits":5},
{"CourseID":76,"Title":"Business Development","Credits":3},
{"CourseID":77,"Title":"Engineering","Credits":2},
{"CourseID":78,"Title":"Sales","Credits":1},
{"CourseID":79,"Title":"Marketing","Credits":5},
{"CourseID":80,"Title":"Marketing","Credits":1},
{"CourseID":81,"Title":"Marketing","Credits":1},
{"CourseID":82,"Title":"Support","Credits":3},
{"CourseID":83,"Title":"Services","Credits":5},
{"CourseID":84,"Title":"Business Development","Credits":4},
{"CourseID":85,"Title":"Research and Development","Credits":3},
{"CourseID":86,"Title":"Product Management","Credits":3},
{"CourseID":87,"Title":"Research and Development","Credits":4},
{"CourseID":88,"Title":"Marketing","Credits":4},
{"CourseID":89,"Title":"Legal","Credits":3},
{"CourseID":90,"Title":"Services","Credits":1},
{"CourseID":91,"Title":"Marketing","Credits":1},
{"CourseID":92,"Title":"Accounting","Credits":4},
{"CourseID":93,"Title":"Sales","Credits":1},
{"CourseID":94,"Title":"Legal","Credits":4},
{"CourseID":95,"Title":"Engineering","Credits":4},
{"CourseID":96,"Title":"Marketing","Credits":4},
{"CourseID":97,"Title":"Sales","Credits":3},
{"CourseID":98,"Title":"Marketing","Credits":4},
{"CourseID":99,"Title":"Research and Development","Credits":1},
{"CourseID":100,"Title":"Accounting","Credits":1},
{"CourseID":101,"Title":"Legal","Credits":2},
{"CourseID":102,"Title":"Training","Credits":1},
{"CourseID":103,"Title":"Legal","Credits":2},
{"CourseID":104,"Title":"Research and Development","Credits":1},
{"CourseID":105,"Title":"Services","Credits":5},
{"CourseID":106,"Title":"Marketing","Credits":4},
{"CourseID":107,"Title":"Accounting","Credits":3},
{"CourseID":108,"Title":"Support","Credits":2},
{"CourseID":109,"Title":"Legal","Credits":2},
{"CourseID":110,"Title":"Engineering","Credits":2},
{"CourseID":111,"Title":"Support","Credits":4},
{"CourseID":112,"Title":"Research and Development","Credits":2},
{"CourseID":113,"Title":"Research and Development","Credits":1},
{"CourseID":114,"Title":"Services","Credits":3},
{"CourseID":115,"Title":"Accounting","Credits":3},
{"CourseID":116,"Title":"Support","Credits":1},
{"CourseID":117,"Title":"Engineering","Credits":1},
{"CourseID":118,"Title":"Marketing","Credits":1},
{"CourseID":119,"Title":"Human Resources","Credits":5},
{"CourseID":120,"Title":"Marketing","Credits":2},
{"CourseID":121,"Title":"Engineering","Credits":3},
{"CourseID":122,"Title":"Product Management","Credits":5},
{"CourseID":123,"Title":"Research and Development","Credits":3},
{"CourseID":124,"Title":"Engineering","Credits":5},
{"CourseID":125,"Title":"Accounting","Credits":2},
{"CourseID":126,"Title":"Training","Credits":3},
{"CourseID":127,"Title":"Business Development","Credits":3},
{"CourseID":128,"Title":"Product Management","Credits":3},
{"CourseID":129,"Title":"Engineering","Credits":2},
{"CourseID":130,"Title":"Legal","Credits":5},
{"CourseID":131,"Title":"Engineering","Credits":4},
{"CourseID":132,"Title":"Business Development","Credits":1},
{"CourseID":133,"Title":"Support","Credits":5},
{"CourseID":134,"Title":"Training","Credits":3},
{"CourseID":135,"Title":"Accounting","Credits":4},
{"CourseID":136,"Title":"Business Development","Credits":1},
{"CourseID":137,"Title":"Research and Development","Credits":4},
{"CourseID":138,"Title":"Support","Credits":2},
{"CourseID":139,"Title":"Engineering","Credits":3},
{"CourseID":140,"Title":"Support","Credits":5},
{"CourseID":141,"Title":"Accounting","Credits":5},
{"CourseID":142,"Title":"Sales","Credits":3},
{"CourseID":143,"Title":"Research and Development","Credits":1},
{"CourseID":144,"Title":"Product Management","Credits":5},
{"CourseID":145,"Title":"Engineering","Credits":4},
{"CourseID":146,"Title":"Services","Credits":1},
{"CourseID":147,"Title":"Product Management","Credits":5},
{"CourseID":148,"Title":"Human Resources","Credits":2},
{"CourseID":149,"Title":"Services","Credits":5},
{"CourseID":150,"Title":"Sales","Credits":1},
{"CourseID":151,"Title":"Services","Credits":5},
{"CourseID":152,"Title":"Accounting","Credits":1},
{"CourseID":153,"Title":"Legal","Credits":4},
{"CourseID":154,"Title":"Product Management","Credits":4},
{"CourseID":155,"Title":"Training","Credits":1},
{"CourseID":156,"Title":"Services","Credits":4},
{"CourseID":157,"Title":"Product Management","Credits":5},
{"CourseID":158,"Title":"Human Resources","Credits":5},
{"CourseID":159,"Title":"Accounting","Credits":1},
{"CourseID":160,"Title":"Services","Credits":5},
{"CourseID":161,"Title":"Marketing","Credits":3},
{"CourseID":162,"Title":"Marketing","Credits":1},
{"CourseID":163,"Title":"Product Management","Credits":5},
{"CourseID":164,"Title":"Services","Credits":1},
{"CourseID":165,"Title":"Engineering","Credits":3},
{"CourseID":166,"Title":"Legal","Credits":3},
{"CourseID":167,"Title":"Training","Credits":5},
{"CourseID":168,"Title":"Support","Credits":2},
{"CourseID":169,"Title":"Engineering","Credits":3},
{"CourseID":170,"Title":"Training","Credits":1},
{"CourseID":171,"Title":"Product Management","Credits":5},
{"CourseID":172,"Title":"Product Management","Credits":1},
{"CourseID":173,"Title":"Engineering","Credits":2},
{"CourseID":174,"Title":"Marketing","Credits":5},
{"CourseID":175,"Title":"Human Resources","Credits":1},
{"CourseID":176,"Title":"Marketing","Credits":3},
{"CourseID":177,"Title":"Business Development","Credits":1},
{"CourseID":178,"Title":"Business Development","Credits":2},
{"CourseID":179,"Title":"Research and Development","Credits":5},
{"CourseID":180,"Title":"Sales","Credits":5},
{"CourseID":181,"Title":"Support","Credits":3},
{"CourseID":182,"Title":"Legal","Credits":5},
{"CourseID":183,"Title":"Business Development","Credits":2},
{"CourseID":184,"Title":"Research and Development","Credits":5},
{"CourseID":185,"Title":"Sales","Credits":3},
{"CourseID":186,"Title":"Marketing","Credits":3},
{"CourseID":187,"Title":"Business Development","Credits":1},
{"CourseID":188,"Title":"Human Resources","Credits":4},
{"CourseID":189,"Title":"Engineering","Credits":2},
{"CourseID":190,"Title":"Services","Credits":5},
{"CourseID":191,"Title":"Business Development","Credits":1},
{"CourseID":192,"Title":"Business Development","Credits":1},
{"CourseID":193,"Title":"Marketing","Credits":4},
{"CourseID":194,"Title":"Services","Credits":1},
{"CourseID":195,"Title":"Engineering","Credits":2},
{"CourseID":196,"Title":"Product Management","Credits":3},
{"CourseID":197,"Title":"Sales","Credits":3},
{"CourseID":198,"Title":"Training","Credits":2},
{"CourseID":199,"Title":"Human Resources","Credits":2},
{"CourseID":200,"Title":"Accounting","Credits":1},
{"CourseID":201,"Title":"Product Management","Credits":3},
{"CourseID":202,"Title":"Product Management","Credits":2},
{"CourseID":203,"Title":"Sales","Credits":4},
{"CourseID":204,"Title":"Product Management","Credits":5},
{"CourseID":205,"Title":"Engineering","Credits":5},
{"CourseID":206,"Title":"Product Management","Credits":3},
{"CourseID":207,"Title":"Accounting","Credits":1},
{"CourseID":208,"Title":"Business Development","Credits":1},
{"CourseID":209,"Title":"Engineering","Credits":1},
{"CourseID":210,"Title":"Marketing","Credits":4},
{"CourseID":211,"Title":"Research and Development","Credits":4},
{"CourseID":212,"Title":"Legal","Credits":1},
{"CourseID":213,"Title":"Business Development","Credits":5},
{"CourseID":214,"Title":"Product Management","Credits":5},
{"CourseID":215,"Title":"Training","Credits":3},
{"CourseID":216,"Title":"Product Management","Credits":5},
{"CourseID":217,"Title":"Marketing","Credits":4},
{"CourseID":218,"Title":"Marketing","Credits":1},
{"CourseID":219,"Title":"Services","Credits":1},
{"CourseID":220,"Title":"Services","Credits":1},
{"CourseID":221,"Title":"Product Management","Credits":3},
{"CourseID":222,"Title":"Research and Development","Credits":2},
{"CourseID":223,"Title":"Business Development","Credits":1},
{"CourseID":224,"Title":"Training","Credits":5},
{"CourseID":225,"Title":"Sales","Credits":3},
{"CourseID":226,"Title":"Sales","Credits":2},
{"CourseID":227,"Title":"Engineering","Credits":4},
{"CourseID":228,"Title":"Legal","Credits":3},
{"CourseID":229,"Title":"Marketing","Credits":2},
{"CourseID":230,"Title":"Engineering","Credits":1},
{"CourseID":231,"Title":"Legal","Credits":1},
{"CourseID":232,"Title":"Support","Credits":2},
{"CourseID":233,"Title":"Business Development","Credits":3},
{"CourseID":234,"Title":"Human Resources","Credits":2},
{"CourseID":235,"Title":"Support","Credits":4},
{"CourseID":236,"Title":"Marketing","Credits":2},
{"CourseID":237,"Title":"Training","Credits":3},
{"CourseID":238,"Title":"Sales","Credits":3},
{"CourseID":239,"Title":"Human Resources","Credits":1},
{"CourseID":240,"Title":"Marketing","Credits":1},
{"CourseID":241,"Title":"Engineering","Credits":2},
{"CourseID":242,"Title":"Sales","Credits":1},
{"CourseID":243,"Title":"Human Resources","Credits":3},
{"CourseID":244,"Title":"Marketing","Credits":4},
{"CourseID":245,"Title":"Legal","Credits":3},
{"CourseID":246,"Title":"Services","Credits":1},
{"CourseID":247,"Title":"Services","Credits":3},
{"CourseID":248,"Title":"Product Management","Credits":5},
{"CourseID":249,"Title":"Marketing","Credits":1},
{"CourseID":250,"Title":"Engineering","Credits":5},
{"CourseID":251,"Title":"Engineering","Credits":2},
{"CourseID":252,"Title":"Human Resources","Credits":4},
{"CourseID":253,"Title":"Business Development","Credits":1},
{"CourseID":254,"Title":"Human Resources","Credits":4},
{"CourseID":255,"Title":"Research and Development","Credits":2},
{"CourseID":256,"Title":"Research and Development","Credits":2},
{"CourseID":257,"Title":"Marketing","Credits":2},
{"CourseID":258,"Title":"Engineering","Credits":2},
{"CourseID":259,"Title":"Business Development","Credits":5},
{"CourseID":260,"Title":"Legal","Credits":1},
{"CourseID":261,"Title":"Services","Credits":3},
{"CourseID":262,"Title":"Research and Development","Credits":4},
{"CourseID":263,"Title":"Product Management","Credits":3},
{"CourseID":264,"Title":"Research and Development","Credits":5},
{"CourseID":265,"Title":"Business Development","Credits":3},
{"CourseID":266,"Title":"Human Resources","Credits":1},
{"CourseID":267,"Title":"Services","Credits":5},
{"CourseID":268,"Title":"Support","Credits":4},
{"CourseID":269,"Title":"Services","Credits":1},
{"CourseID":270,"Title":"Human Resources","Credits":5},
{"CourseID":271,"Title":"Support","Credits":2},
{"CourseID":272,"Title":"Product Management","Credits":1},
{"CourseID":273,"Title":"Product Management","Credits":3},
{"CourseID":274,"Title":"Services","Credits":5},
{"CourseID":275,"Title":"Services","Credits":5},
{"CourseID":276,"Title":"Human Resources","Credits":2},
{"CourseID":277,"Title":"Services","Credits":4},
{"CourseID":278,"Title":"Product Management","Credits":4},
{"CourseID":279,"Title":"Marketing","Credits":5},
{"CourseID":280,"Title":"Engineering","Credits":5},
{"CourseID":281,"Title":"Marketing","Credits":5},
{"CourseID":282,"Title":"Support","Credits":3},
{"CourseID":283,"Title":"Training","Credits":4},
{"CourseID":284,"Title":"Accounting","Credits":1},
{"CourseID":285,"Title":"Services","Credits":2},
{"CourseID":286,"Title":"Human Resources","Credits":3},
{"CourseID":287,"Title":"Training","Credits":4},
{"CourseID":288,"Title":"Services","Credits":3},
{"CourseID":289,"Title":"Human Resources","Credits":1},
{"CourseID":290,"Title":"Accounting","Credits":3},
{"CourseID":291,"Title":"Human Resources","Credits":5},
{"CourseID":292,"Title":"Human Resources","Credits":4},
{"CourseID":293,"Title":"Legal","Credits":3},
{"CourseID":294,"Title":"Engineering","Credits":5},
{"CourseID":295,"Title":"Sales","Credits":5},
{"CourseID":296,"Title":"Training","Credits":3},
{"CourseID":297,"Title":"Business Development","Credits":3},
{"CourseID":298,"Title":"Research and Development","Credits":3},
{"CourseID":299,"Title":"Engineering","Credits":5},
{"CourseID":300,"Title":"Human Resources","Credits":2},
{"CourseID":301,"Title":"Support","Credits":2},
{"CourseID":302,"Title":"Support","Credits":5},
{"CourseID":303,"Title":"Business Development","Credits":3},
{"CourseID":304,"Title":"Sales","Credits":2},
{"CourseID":305,"Title":"Accounting","Credits":4},
{"CourseID":306,"Title":"Business Development","Credits":1},
{"CourseID":307,"Title":"Product Management","Credits":2},
{"CourseID":308,"Title":"Product Management","Credits":3},
{"CourseID":309,"Title":"Training","Credits":1},
{"CourseID":310,"Title":"Sales","Credits":1},
{"CourseID":311,"Title":"Marketing","Credits":2},
{"CourseID":312,"Title":"Business Development","Credits":4},
{"CourseID":313,"Title":"Marketing","Credits":3},
{"CourseID":314,"Title":"Services","Credits":3},
{"CourseID":315,"Title":"Product Management","Credits":4},
{"CourseID":316,"Title":"Research and Development","Credits":3},
{"CourseID":317,"Title":"Services","Credits":1},
{"CourseID":318,"Title":"Services","Credits":5},
{"CourseID":319,"Title":"Research and Development","Credits":3},
{"CourseID":320,"Title":"Engineering","Credits":4},
{"CourseID":321,"Title":"Human Resources","Credits":3},
{"CourseID":322,"Title":"Business Development","Credits":2},
{"CourseID":323,"Title":"Engineering","Credits":2},
{"CourseID":324,"Title":"Training","Credits":4},
{"CourseID":325,"Title":"Engineering","Credits":5},
{"CourseID":326,"Title":"Human Resources","Credits":4},
{"CourseID":327,"Title":"Marketing","Credits":2},
{"CourseID":328,"Title":"Support","Credits":2},
{"CourseID":329,"Title":"Research and Development","Credits":1},
{"CourseID":330,"Title":"Legal","Credits":3},
{"CourseID":331,"Title":"Sales","Credits":5},
{"CourseID":332,"Title":"Marketing","Credits":1},
{"CourseID":333,"Title":"Support","Credits":4},
{"CourseID":334,"Title":"Training","Credits":3},
{"CourseID":335,"Title":"Sales","Credits":2},
{"CourseID":336,"Title":"Human Resources","Credits":4},
{"CourseID":337,"Title":"Business Development","Credits":2},
{"CourseID":338,"Title":"Support","Credits":5},
{"CourseID":339,"Title":"Product Management","Credits":5},
{"CourseID":340,"Title":"Business Development","Credits":1},
{"CourseID":341,"Title":"Product Management","Credits":3},
{"CourseID":342,"Title":"Legal","Credits":5},
{"CourseID":343,"Title":"Business Development","Credits":2},
{"CourseID":344,"Title":"Business Development","Credits":5},
{"CourseID":345,"Title":"Business Development","Credits":4},
{"CourseID":346,"Title":"Product Management","Credits":5},
{"CourseID":347,"Title":"Business Development","Credits":4},
{"CourseID":348,"Title":"Business Development","Credits":2},
{"CourseID":349,"Title":"Services","Credits":5},
{"CourseID":350,"Title":"Marketing","Credits":5},
{"CourseID":351,"Title":"Services","Credits":4},
{"CourseID":352,"Title":"Sales","Credits":3},
{"CourseID":353,"Title":"Product Management","Credits":4},
{"CourseID":354,"Title":"Engineering","Credits":3},
{"CourseID":355,"Title":"Accounting","Credits":5},
{"CourseID":356,"Title":"Business Development","Credits":1},
{"CourseID":357,"Title":"Research and Development","Credits":3},
{"CourseID":358,"Title":"Human Resources","Credits":3},
{"CourseID":359,"Title":"Business Development","Credits":2},
{"CourseID":360,"Title":"Training","Credits":5},
{"CourseID":361,"Title":"Services","Credits":5},
{"CourseID":362,"Title":"Human Resources","Credits":4},
{"CourseID":363,"Title":"Human Resources","Credits":4},
{"CourseID":364,"Title":"Product Management","Credits":4},
{"CourseID":365,"Title":"Business Development","Credits":1},
{"CourseID":366,"Title":"Research and Development","Credits":5},
{"CourseID":367,"Title":"Marketing","Credits":4},
{"CourseID":368,"Title":"Product Management","Credits":5},
{"CourseID":369,"Title":"Research and Development","Credits":5},
{"CourseID":370,"Title":"Business Development","Credits":5},
{"CourseID":371,"Title":"Legal","Credits":5},
{"CourseID":372,"Title":"Product Management","Credits":2},
{"CourseID":373,"Title":"Legal","Credits":2},
{"CourseID":374,"Title":"Research and Development","Credits":1},
{"CourseID":375,"Title":"Product Management","Credits":3},
{"CourseID":376,"Title":"Engineering","Credits":1},
{"CourseID":377,"Title":"Sales","Credits":2},
{"CourseID":378,"Title":"Services","Credits":3},
{"CourseID":379,"Title":"Research and Development","Credits":2},
{"CourseID":380,"Title":"Business Development","Credits":4},
{"CourseID":381,"Title":"Engineering","Credits":2},
{"CourseID":382,"Title":"Support","Credits":2},
{"CourseID":383,"Title":"Research and Development","Credits":3},
{"CourseID":384,"Title":"Training","Credits":5},
{"CourseID":385,"Title":"Product Management","Credits":2},
{"CourseID":386,"Title":"Human Resources","Credits":5},
{"CourseID":387,"Title":"Sales","Credits":1},
{"CourseID":388,"Title":"Legal","Credits":4},
{"CourseID":389,"Title":"Accounting","Credits":4},
{"CourseID":390,"Title":"Accounting","Credits":5},
{"CourseID":391,"Title":"Services","Credits":4},
{"CourseID":392,"Title":"Accounting","Credits":4},
{"CourseID":393,"Title":"Accounting","Credits":4},
{"CourseID":394,"Title":"Marketing","Credits":1},
{"CourseID":395,"Title":"Sales","Credits":5},
{"CourseID":396,"Title":"Business Development","Credits":1},
{"CourseID":397,"Title":"Business Development","Credits":1},
{"CourseID":398,"Title":"Accounting","Credits":5},
{"CourseID":399,"Title":"Research and Development","Credits":2},
{"CourseID":400,"Title":"Training","Credits":1},
{"CourseID":401,"Title":"Legal","Credits":1},
{"CourseID":402,"Title":"Support","Credits":4},
{"CourseID":403,"Title":"Sales","Credits":4},
{"CourseID":404,"Title":"Marketing","Credits":1},
{"CourseID":405,"Title":"Training","Credits":2},
{"CourseID":406,"Title":"Support","Credits":2},
{"CourseID":407,"Title":"Sales","Credits":3},
{"CourseID":408,"Title":"Legal","Credits":3},
{"CourseID":409,"Title":"Product Management","Credits":3},
{"CourseID":410,"Title":"Human Resources","Credits":4},
{"CourseID":411,"Title":"Product Management","Credits":5},
{"CourseID":412,"Title":"Services","Credits":3},
{"CourseID":413,"Title":"Legal","Credits":1},
{"CourseID":414,"Title":"Human Resources","Credits":1},
{"CourseID":415,"Title":"Product Management","Credits":5},
{"CourseID":416,"Title":"Accounting","Credits":3},
{"CourseID":417,"Title":"Support","Credits":5},
{"CourseID":418,"Title":"Product Management","Credits":4},
{"CourseID":419,"Title":"Accounting","Credits":5},
{"CourseID":420,"Title":"Training","Credits":3},
{"CourseID":421,"Title":"Marketing","Credits":3},
{"CourseID":422,"Title":"Accounting","Credits":2},
{"CourseID":423,"Title":"Research and Development","Credits":2},
{"CourseID":424,"Title":"Training","Credits":4},
{"CourseID":425,"Title":"Marketing","Credits":4},
{"CourseID":426,"Title":"Marketing","Credits":3},
{"CourseID":427,"Title":"Legal","Credits":1},
{"CourseID":428,"Title":"Research and Development","Credits":2},
{"CourseID":429,"Title":"Support","Credits":4},
{"CourseID":430,"Title":"Human Resources","Credits":4},
{"CourseID":431,"Title":"Training","Credits":4},
{"CourseID":432,"Title":"Support","Credits":1},
{"CourseID":433,"Title":"Sales","Credits":4},
{"CourseID":434,"Title":"Business Development","Credits":1},
{"CourseID":435,"Title":"Legal","Credits":2},
{"CourseID":436,"Title":"Support","Credits":3},
{"CourseID":437,"Title":"Product Management","Credits":1},
{"CourseID":438,"Title":"Support","Credits":2},
{"CourseID":439,"Title":"Accounting","Credits":3},
{"CourseID":440,"Title":"Business Development","Credits":3},
{"CourseID":441,"Title":"Legal","Credits":4},
{"CourseID":442,"Title":"Business Development","Credits":5},
{"CourseID":443,"Title":"Product Management","Credits":2},
{"CourseID":444,"Title":"Marketing","Credits":4},
{"CourseID":445,"Title":"Training","Credits":1},
{"CourseID":446,"Title":"Services","Credits":1},
{"CourseID":447,"Title":"Business Development","Credits":2},
{"CourseID":448,"Title":"Business Development","Credits":4},
{"CourseID":449,"Title":"Business Development","Credits":5},
{"CourseID":450,"Title":"Support","Credits":5},
{"CourseID":451,"Title":"Product Management","Credits":1},
{"CourseID":452,"Title":"Research and Development","Credits":2},
{"CourseID":453,"Title":"Support","Credits":2},
{"CourseID":454,"Title":"Human Resources","Credits":4},
{"CourseID":455,"Title":"Training","Credits":2},
{"CourseID":456,"Title":"Services","Credits":1},
{"CourseID":457,"Title":"Research and Development","Credits":2},
{"CourseID":458,"Title":"Marketing","Credits":2},
{"CourseID":459,"Title":"Services","Credits":3},
{"CourseID":460,"Title":"Human Resources","Credits":1},
{"CourseID":461,"Title":"Support","Credits":2},
{"CourseID":462,"Title":"Accounting","Credits":3},
{"CourseID":463,"Title":"Accounting","Credits":5},
{"CourseID":464,"Title":"Product Management","Credits":2},
{"CourseID":465,"Title":"Research and Development","Credits":2},
{"CourseID":466,"Title":"Training","Credits":3},
{"CourseID":467,"Title":"Legal","Credits":2},
{"CourseID":468,"Title":"Product Management","Credits":5},
{"CourseID":469,"Title":"Training","Credits":1},
{"CourseID":470,"Title":"Services","Credits":4},
{"CourseID":471,"Title":"Product Management","Credits":3},
{"CourseID":472,"Title":"Business Development","Credits":4},
{"CourseID":473,"Title":"Product Management","Credits":5},
{"CourseID":474,"Title":"Human Resources","Credits":1},
{"CourseID":475,"Title":"Services","Credits":5},
{"CourseID":476,"Title":"Legal","Credits":1},
{"CourseID":477,"Title":"Human Resources","Credits":2},
{"CourseID":478,"Title":"Services","Credits":2},
{"CourseID":479,"Title":"Human Resources","Credits":1},
{"CourseID":480,"Title":"Accounting","Credits":2},
{"CourseID":481,"Title":"Research and Development","Credits":1},
{"CourseID":482,"Title":"Services","Credits":5},
{"CourseID":483,"Title":"Research and Development","Credits":4},
{"CourseID":484,"Title":"Human Resources","Credits":3},
{"CourseID":485,"Title":"Training","Credits":2},
{"CourseID":486,"Title":"Business Development","Credits":1},
{"CourseID":487,"Title":"Sales","Credits":1},
{"CourseID":488,"Title":"Marketing","Credits":2},
{"CourseID":489,"Title":"Engineering","Credits":5},
{"CourseID":490,"Title":"Product Management","Credits":3},
{"CourseID":491,"Title":"Human Resources","Credits":4},
{"CourseID":492,"Title":"Support","Credits":1},
{"CourseID":493,"Title":"Research and Development","Credits":1},
{"CourseID":494,"Title":"Business Development","Credits":1},
{"CourseID":495,"Title":"Accounting","Credits":2},
{"CourseID":496,"Title":"Accounting","Credits":3},
{"CourseID":497,"Title":"Research and Development","Credits":1},
{"CourseID":498,"Title":"Human Resources","Credits":3},
{"CourseID":499,"Title":"Accounting","Credits":3},
{"CourseID":500,"Title":"Product Management","Credits":1},
{"CourseID":501,"Title":"Support","Credits":2},
{"CourseID":502,"Title":"Human Resources","Credits":3},
{"CourseID":503,"Title":"Services","Credits":2},
{"CourseID":504,"Title":"Marketing","Credits":1},
{"CourseID":505,"Title":"Product Management","Credits":2},
{"CourseID":506,"Title":"Engineering","Credits":2},
{"CourseID":507,"Title":"Support","Credits":5},
{"CourseID":508,"Title":"Human Resources","Credits":2},
{"CourseID":509,"Title":"Research and Development","Credits":4},
{"CourseID":510,"Title":"Legal","Credits":4},
{"CourseID":511,"Title":"Support","Credits":2},
{"CourseID":512,"Title":"Training","Credits":1},
{"CourseID":513,"Title":"Accounting","Credits":5},
{"CourseID":514,"Title":"Training","Credits":1},
{"CourseID":515,"Title":"Training","Credits":4},
{"CourseID":516,"Title":"Services","Credits":1},
{"CourseID":517,"Title":"Accounting","Credits":3},
{"CourseID":518,"Title":"Human Resources","Credits":5},
{"CourseID":519,"Title":"Legal","Credits":3},
{"CourseID":520,"Title":"Marketing","Credits":5},
{"CourseID":521,"Title":"Training","Credits":3},
{"CourseID":522,"Title":"Engineering","Credits":3},
{"CourseID":523,"Title":"Accounting","Credits":1},
{"CourseID":524,"Title":"Support","Credits":3},
{"CourseID":525,"Title":"Business Development","Credits":5},
{"CourseID":526,"Title":"Research and Development","Credits":1},
{"CourseID":527,"Title":"Accounting","Credits":1},
{"CourseID":528,"Title":"Sales","Credits":2},
{"CourseID":529,"Title":"Training","Credits":5},
{"CourseID":530,"Title":"Marketing","Credits":1},
{"CourseID":531,"Title":"Engineering","Credits":5},
{"CourseID":532,"Title":"Legal","Credits":5},
{"CourseID":533,"Title":"Training","Credits":3},
{"CourseID":534,"Title":"Business Development","Credits":3},
{"CourseID":535,"Title":"Sales","Credits":2},
{"CourseID":536,"Title":"Support","Credits":2},
{"CourseID":537,"Title":"Marketing","Credits":2},
{"CourseID":538,"Title":"Product Management","Credits":5},
{"CourseID":539,"Title":"Legal","Credits":4},
{"CourseID":540,"Title":"Services","Credits":3},
{"CourseID":541,"Title":"Accounting","Credits":3},
{"CourseID":542,"Title":"Business Development","Credits":2},
{"CourseID":543,"Title":"Accounting","Credits":4},
{"CourseID":544,"Title":"Engineering","Credits":2},
{"CourseID":545,"Title":"Human Resources","Credits":4},
{"CourseID":546,"Title":"Training","Credits":1},
{"CourseID":547,"Title":"Training","Credits":5},
{"CourseID":548,"Title":"Business Development","Credits":4},
{"CourseID":549,"Title":"Business Development","Credits":3},
{"CourseID":550,"Title":"Accounting","Credits":5},
{"CourseID":551,"Title":"Marketing","Credits":2},
{"CourseID":552,"Title":"Marketing","Credits":2},
{"CourseID":553,"Title":"Research and Development","Credits":2},
{"CourseID":554,"Title":"Engineering","Credits":5},
{"CourseID":555,"Title":"Accounting","Credits":4},
{"CourseID":556,"Title":"Training","Credits":5},
{"CourseID":557,"Title":"Training","Credits":3},
{"CourseID":558,"Title":"Product Management","Credits":4},
{"CourseID":559,"Title":"Support","Credits":5},
{"CourseID":560,"Title":"Human Resources","Credits":5},
{"CourseID":561,"Title":"Product Management","Credits":5},
{"CourseID":562,"Title":"Services","Credits":5},
{"CourseID":563,"Title":"Accounting","Credits":5},
{"CourseID":564,"Title":"Support","Credits":2},
{"CourseID":565,"Title":"Human Resources","Credits":5},
{"CourseID":566,"Title":"Legal","Credits":5},
{"CourseID":567,"Title":"Business Development","Credits":5},
{"CourseID":568,"Title":"Research and Development","Credits":5},
{"CourseID":569,"Title":"Marketing","Credits":1},
{"CourseID":570,"Title":"Sales","Credits":5},
{"CourseID":571,"Title":"Business Development","Credits":3},
{"CourseID":572,"Title":"Legal","Credits":3},
{"CourseID":573,"Title":"Accounting","Credits":4},
{"CourseID":574,"Title":"Legal","Credits":1},
{"CourseID":575,"Title":"Engineering","Credits":5},
{"CourseID":576,"Title":"Business Development","Credits":3},
{"CourseID":577,"Title":"Business Development","Credits":1},
{"CourseID":578,"Title":"Training","Credits":3},
{"CourseID":579,"Title":"Human Resources","Credits":4},
{"CourseID":580,"Title":"Human Resources","Credits":4},
{"CourseID":581,"Title":"Support","Credits":5},
{"CourseID":582,"Title":"Engineering","Credits":5},
{"CourseID":583,"Title":"Research and Development","Credits":2},
{"CourseID":584,"Title":"Marketing","Credits":4},
{"CourseID":585,"Title":"Product Management","Credits":5},
{"CourseID":586,"Title":"Business Development","Credits":2},
{"CourseID":587,"Title":"Services","Credits":1},
{"CourseID":588,"Title":"Support","Credits":4},
{"CourseID":589,"Title":"Human Resources","Credits":4},
{"CourseID":590,"Title":"Accounting","Credits":3},
{"CourseID":591,"Title":"Human Resources","Credits":2},
{"CourseID":592,"Title":"Support","Credits":2},
{"CourseID":593,"Title":"Sales","Credits":1},
{"CourseID":594,"Title":"Accounting","Credits":3},
{"CourseID":595,"Title":"Sales","Credits":3},
{"CourseID":596,"Title":"Accounting","Credits":2},
{"CourseID":597,"Title":"Sales","Credits":1},
{"CourseID":598,"Title":"Engineering","Credits":5},
{"CourseID":599,"Title":"Services","Credits":2},
{"CourseID":600,"Title":"Marketing","Credits":1},
{"CourseID":601,"Title":"Accounting","Credits":3},
{"CourseID":602,"Title":"Legal","Credits":5},
{"CourseID":603,"Title":"Research and Development","Credits":3},
{"CourseID":604,"Title":"Human Resources","Credits":2},
{"CourseID":605,"Title":"Support","Credits":4},
{"CourseID":606,"Title":"Engineering","Credits":1},
{"CourseID":607,"Title":"Sales","Credits":4},
{"CourseID":608,"Title":"Human Resources","Credits":5},
{"CourseID":609,"Title":"Services","Credits":3},
{"CourseID":610,"Title":"Product Management","Credits":1},
{"CourseID":611,"Title":"Legal","Credits":5},
{"CourseID":612,"Title":"Business Development","Credits":2},
{"CourseID":613,"Title":"Engineering","Credits":4},
{"CourseID":614,"Title":"Legal","Credits":5},
{"CourseID":615,"Title":"Services","Credits":1},
{"CourseID":616,"Title":"Human Resources","Credits":5},
{"CourseID":617,"Title":"Engineering","Credits":3},
{"CourseID":618,"Title":"Accounting","Credits":1},
{"CourseID":619,"Title":"Product Management","Credits":4},
{"CourseID":620,"Title":"Engineering","Credits":5},
{"CourseID":621,"Title":"Engineering","Credits":2},
{"CourseID":622,"Title":"Human Resources","Credits":2},
{"CourseID":623,"Title":"Human Resources","Credits":1},
{"CourseID":624,"Title":"Training","Credits":2},
{"CourseID":625,"Title":"Training","Credits":5},
{"CourseID":626,"Title":"Support","Credits":2},
{"CourseID":627,"Title":"Support","Credits":1},
{"CourseID":628,"Title":"Training","Credits":2},
{"CourseID":629,"Title":"Legal","Credits":3},
{"CourseID":630,"Title":"Accounting","Credits":4},
{"CourseID":631,"Title":"Support","Credits":2},
{"CourseID":632,"Title":"Accounting","Credits":4},
{"CourseID":633,"Title":"Product Management","Credits":4},
{"CourseID":634,"Title":"Marketing","Credits":1},
{"CourseID":635,"Title":"Sales","Credits":2},
{"CourseID":636,"Title":"Engineering","Credits":5},
{"CourseID":637,"Title":"Business Development","Credits":2},
{"CourseID":638,"Title":"Accounting","Credits":2},
{"CourseID":639,"Title":"Support","Credits":2},
{"CourseID":640,"Title":"Engineering","Credits":1},
{"CourseID":641,"Title":"Marketing","Credits":2},
{"CourseID":642,"Title":"Accounting","Credits":3},
{"CourseID":643,"Title":"Training","Credits":2},
{"CourseID":644,"Title":"Product Management","Credits":4},
{"CourseID":645,"Title":"Services","Credits":5},
{"CourseID":646,"Title":"Product Management","Credits":3},
{"CourseID":647,"Title":"Sales","Credits":5},
{"CourseID":648,"Title":"Product Management","Credits":4},
{"CourseID":649,"Title":"Support","Credits":1},
{"CourseID":650,"Title":"Accounting","Credits":2},
{"CourseID":651,"Title":"Sales","Credits":2},
{"CourseID":652,"Title":"Research and Development","Credits":4},
{"CourseID":653,"Title":"Business Development","Credits":4},
{"CourseID":654,"Title":"Human Resources","Credits":1},
{"CourseID":655,"Title":"Research and Development","Credits":1},
{"CourseID":656,"Title":"Legal","Credits":1},
{"CourseID":657,"Title":"Marketing","Credits":1},
{"CourseID":658,"Title":"Accounting","Credits":3},
{"CourseID":659,"Title":"Services","Credits":2},
{"CourseID":660,"Title":"Support","Credits":4},
{"CourseID":661,"Title":"Marketing","Credits":4},
{"CourseID":662,"Title":"Engineering","Credits":4},
{"CourseID":663,"Title":"Training","Credits":3},
{"CourseID":664,"Title":"Legal","Credits":3},
{"CourseID":665,"Title":"Human Resources","Credits":4},
{"CourseID":666,"Title":"Product Management","Credits":5},
{"CourseID":667,"Title":"Business Development","Credits":5},
{"CourseID":668,"Title":"Accounting","Credits":1},
{"CourseID":669,"Title":"Product Management","Credits":5},
{"CourseID":670,"Title":"Support","Credits":2},
{"CourseID":671,"Title":"Training","Credits":1},
{"CourseID":672,"Title":"Engineering","Credits":2},
{"CourseID":673,"Title":"Sales","Credits":4},
{"CourseID":674,"Title":"Research and Development","Credits":3},
{"CourseID":675,"Title":"Research and Development","Credits":3},
{"CourseID":676,"Title":"Marketing","Credits":5},
{"CourseID":677,"Title":"Sales","Credits":3},
{"CourseID":678,"Title":"Support","Credits":4},
{"CourseID":679,"Title":"Legal","Credits":3},
{"CourseID":680,"Title":"Engineering","Credits":3},
{"CourseID":681,"Title":"Support","Credits":5},
{"CourseID":682,"Title":"Human Resources","Credits":4},
{"CourseID":683,"Title":"Support","Credits":5},
{"CourseID":684,"Title":"Research and Development","Credits":1},
{"CourseID":685,"Title":"Training","Credits":3},
{"CourseID":686,"Title":"Training","Credits":4},
{"CourseID":687,"Title":"Accounting","Credits":3},
{"CourseID":688,"Title":"Product Management","Credits":2},
{"CourseID":689,"Title":"Marketing","Credits":1},
{"CourseID":690,"Title":"Research and Development","Credits":2},
{"CourseID":691,"Title":"Human Resources","Credits":4},
{"CourseID":692,"Title":"Product Management","Credits":4},
{"CourseID":693,"Title":"Legal","Credits":4},
{"CourseID":694,"Title":"Business Development","Credits":3},
{"CourseID":695,"Title":"Marketing","Credits":3},
{"CourseID":696,"Title":"Legal","Credits":5},
{"CourseID":697,"Title":"Product Management","Credits":5},
{"CourseID":698,"Title":"Business Development","Credits":5},
{"CourseID":699,"Title":"Services","Credits":2},
{"CourseID":700,"Title":"Support","Credits":1},
{"CourseID":701,"Title":"Product Management","Credits":1},
{"CourseID":702,"Title":"Sales","Credits":2},
{"CourseID":703,"Title":"Support","Credits":2},
{"CourseID":704,"Title":"Services","Credits":3},
{"CourseID":705,"Title":"Product Management","Credits":3},
{"CourseID":706,"Title":"Sales","Credits":3},
{"CourseID":707,"Title":"Services","Credits":3},
{"CourseID":708,"Title":"Marketing","Credits":2},
{"CourseID":709,"Title":"Marketing","Credits":4},
{"CourseID":710,"Title":"Engineering","Credits":3},
{"CourseID":711,"Title":"Support","Credits":2},
{"CourseID":712,"Title":"Product Management","Credits":2},
{"CourseID":713,"Title":"Human Resources","Credits":5},
{"CourseID":714,"Title":"Services","Credits":4},
{"CourseID":715,"Title":"Training","Credits":4},
{"CourseID":716,"Title":"Services","Credits":2},
{"CourseID":717,"Title":"Engineering","Credits":5},
{"CourseID":718,"Title":"Business Development","Credits":1},
{"CourseID":719,"Title":"Research and Development","Credits":5},
{"CourseID":720,"Title":"Research and Development","Credits":1},
{"CourseID":721,"Title":"Business Development","Credits":5},
{"CourseID":722,"Title":"Services","Credits":5},
{"CourseID":723,"Title":"Business Development","Credits":3},
{"CourseID":724,"Title":"Marketing","Credits":4},
{"CourseID":725,"Title":"Human Resources","Credits":2},
{"CourseID":726,"Title":"Services","Credits":4},
{"CourseID":727,"Title":"Accounting","Credits":3},
{"CourseID":728,"Title":"Services","Credits":2},
{"CourseID":729,"Title":"Research and Development","Credits":4},
{"CourseID":730,"Title":"Training","Credits":5},
{"CourseID":731,"Title":"Business Development","Credits":3},
{"CourseID":732,"Title":"Business Development","Credits":5},
{"CourseID":733,"Title":"Legal","Credits":3},
{"CourseID":734,"Title":"Legal","Credits":2},
{"CourseID":735,"Title":"Research and Development","Credits":1},
{"CourseID":736,"Title":"Business Development","Credits":3},
{"CourseID":737,"Title":"Services","Credits":4},
{"CourseID":738,"Title":"Services","Credits":4},
{"CourseID":739,"Title":"Marketing","Credits":5},
{"CourseID":740,"Title":"Sales","Credits":3},
{"CourseID":741,"Title":"Product Management","Credits":1},
{"CourseID":742,"Title":"Business Development","Credits":3},
{"CourseID":743,"Title":"Business Development","Credits":3},
{"CourseID":744,"Title":"Research and Development","Credits":2},
{"CourseID":745,"Title":"Legal","Credits":3},
{"CourseID":746,"Title":"Support","Credits":1},
{"CourseID":747,"Title":"Research and Development","Credits":5},
{"CourseID":748,"Title":"Human Resources","Credits":4},
{"CourseID":749,"Title":"Human Resources","Credits":2},
{"CourseID":750,"Title":"Product Management","Credits":3},
{"CourseID":751,"Title":"Accounting","Credits":5},
{"CourseID":752,"Title":"Business Development","Credits":2},
{"CourseID":753,"Title":"Training","Credits":3},
{"CourseID":754,"Title":"Services","Credits":2},
{"CourseID":755,"Title":"Marketing","Credits":1},
{"CourseID":756,"Title":"Marketing","Credits":4},
{"CourseID":757,"Title":"Services","Credits":2},
{"CourseID":758,"Title":"Sales","Credits":5},
{"CourseID":759,"Title":"Marketing","Credits":5},
{"CourseID":760,"Title":"Support","Credits":1},
{"CourseID":761,"Title":"Research and Development","Credits":2},
{"CourseID":762,"Title":"Services","Credits":2},
{"CourseID":763,"Title":"Engineering","Credits":5},
{"CourseID":764,"Title":"Legal","Credits":2},
{"CourseID":765,"Title":"Accounting","Credits":4},
{"CourseID":766,"Title":"Support","Credits":4},
{"CourseID":767,"Title":"Support","Credits":3},
{"CourseID":768,"Title":"Accounting","Credits":2},
{"CourseID":769,"Title":"Sales","Credits":4},
{"CourseID":770,"Title":"Engineering","Credits":3},
{"CourseID":771,"Title":"Services","Credits":5},
{"CourseID":772,"Title":"Research and Development","Credits":2},
{"CourseID":773,"Title":"Accounting","Credits":4},
{"CourseID":774,"Title":"Legal","Credits":3},
{"CourseID":775,"Title":"Research and Development","Credits":3},
{"CourseID":776,"Title":"Research and Development","Credits":3},
{"CourseID":777,"Title":"Engineering","Credits":2},
{"CourseID":778,"Title":"Product Management","Credits":1},
{"CourseID":779,"Title":"Business Development","Credits":4},
{"CourseID":780,"Title":"Training","Credits":3},
{"CourseID":781,"Title":"Engineering","Credits":4},
{"CourseID":782,"Title":"Legal","Credits":5},
{"CourseID":783,"Title":"Legal","Credits":1},
{"CourseID":784,"Title":"Training","Credits":5},
{"CourseID":785,"Title":"Human Resources","Credits":5},
{"CourseID":786,"Title":"Research and Development","Credits":1},
{"CourseID":787,"Title":"Research and Development","Credits":3},
{"CourseID":788,"Title":"Legal","Credits":2},
{"CourseID":789,"Title":"Research and Development","Credits":4},
{"CourseID":790,"Title":"Research and Development","Credits":5},
{"CourseID":791,"Title":"Product Management","Credits":3},
{"CourseID":792,"Title":"Accounting","Credits":3},
{"CourseID":793,"Title":"Engineering","Credits":2},
{"CourseID":794,"Title":"Support","Credits":5},
{"CourseID":795,"Title":"Sales","Credits":3},
{"CourseID":796,"Title":"Human Resources","Credits":4},
{"CourseID":797,"Title":"Services","Credits":2},
{"CourseID":798,"Title":"Business Development","Credits":5},
{"CourseID":799,"Title":"Accounting","Credits":3},
{"CourseID":800,"Title":"Engineering","Credits":4},
{"CourseID":801,"Title":"Business Development","Credits":5},
{"CourseID":802,"Title":"Business Development","Credits":5},
{"CourseID":803,"Title":"Training","Credits":5},
{"CourseID":804,"Title":"Support","Credits":3},
{"CourseID":805,"Title":"Services","Credits":1},
{"CourseID":806,"Title":"Support","Credits":4},
{"CourseID":807,"Title":"Accounting","Credits":2},
{"CourseID":808,"Title":"Training","Credits":1},
{"CourseID":809,"Title":"Research and Development","Credits":1},
{"CourseID":810,"Title":"Product Management","Credits":4},
{"CourseID":811,"Title":"Sales","Credits":1},
{"CourseID":812,"Title":"Marketing","Credits":5},
{"CourseID":813,"Title":"Services","Credits":4},
{"CourseID":814,"Title":"Legal","Credits":5},
{"CourseID":815,"Title":"Marketing","Credits":3},
{"CourseID":816,"Title":"Training","Credits":3},
{"CourseID":817,"Title":"Training","Credits":4},
{"CourseID":818,"Title":"Legal","Credits":5},
{"CourseID":819,"Title":"Research and Development","Credits":5},
{"CourseID":820,"Title":"Product Management","Credits":5},
{"CourseID":821,"Title":"Product Management","Credits":1},
{"CourseID":822,"Title":"Accounting","Credits":1},
{"CourseID":823,"Title":"Human Resources","Credits":1},
{"CourseID":824,"Title":"Product Management","Credits":2},
{"CourseID":825,"Title":"Human Resources","Credits":2},
{"CourseID":826,"Title":"Services","Credits":3},
{"CourseID":827,"Title":"Training","Credits":2},
{"CourseID":828,"Title":"Product Management","Credits":2},
{"CourseID":829,"Title":"Marketing","Credits":1},
{"CourseID":830,"Title":"Product Management","Credits":1},
{"CourseID":831,"Title":"Services","Credits":5},
{"CourseID":832,"Title":"Research and Development","Credits":3},
{"CourseID":833,"Title":"Sales","Credits":5},
{"CourseID":834,"Title":"Product Management","Credits":5},
{"CourseID":835,"Title":"Sales","Credits":4},
{"CourseID":836,"Title":"Legal","Credits":1},
{"CourseID":837,"Title":"Business Development","Credits":1},
{"CourseID":838,"Title":"Engineering","Credits":4},
{"CourseID":839,"Title":"Product Management","Credits":3},
{"CourseID":840,"Title":"Human Resources","Credits":5},
{"CourseID":841,"Title":"Marketing","Credits":4},
{"CourseID":842,"Title":"Legal","Credits":5},
{"CourseID":843,"Title":"Marketing","Credits":1},
{"CourseID":844,"Title":"Research and Development","Credits":2},
{"CourseID":845,"Title":"Marketing","Credits":5},
{"CourseID":846,"Title":"Sales","Credits":1},
{"CourseID":847,"Title":"Training","Credits":1},
{"CourseID":848,"Title":"Accounting","Credits":4},
{"CourseID":849,"Title":"Sales","Credits":3},
{"CourseID":850,"Title":"Support","Credits":3},
{"CourseID":851,"Title":"Accounting","Credits":2},
{"CourseID":852,"Title":"Sales","Credits":5},
{"CourseID":853,"Title":"Support","Credits":5},
{"CourseID":854,"Title":"Legal","Credits":3},
{"CourseID":855,"Title":"Product Management","Credits":1},
{"CourseID":856,"Title":"Legal","Credits":4},
{"CourseID":857,"Title":"Services","Credits":5},
{"CourseID":858,"Title":"Engineering","Credits":5},
{"CourseID":859,"Title":"Human Resources","Credits":4},
{"CourseID":860,"Title":"Product Management","Credits":1},
{"CourseID":861,"Title":"Sales","Credits":1},
{"CourseID":862,"Title":"Human Resources","Credits":1},
{"CourseID":863,"Title":"Business Development","Credits":4},
{"CourseID":864,"Title":"Sales","Credits":1},
{"CourseID":865,"Title":"Support","Credits":1},
{"CourseID":866,"Title":"Accounting","Credits":1},
{"CourseID":867,"Title":"Accounting","Credits":4},
{"CourseID":868,"Title":"Services","Credits":4},
{"CourseID":869,"Title":"Support","Credits":5},
{"CourseID":870,"Title":"Human Resources","Credits":1},
{"CourseID":871,"Title":"Training","Credits":3},
{"CourseID":872,"Title":"Product Management","Credits":4},
{"CourseID":873,"Title":"Product Management","Credits":1},
{"CourseID":874,"Title":"Human Resources","Credits":5},
{"CourseID":875,"Title":"Legal","Credits":1},
{"CourseID":876,"Title":"Product Management","Credits":2},
{"CourseID":877,"Title":"Human Resources","Credits":3},
{"CourseID":878,"Title":"Legal","Credits":2},
{"CourseID":879,"Title":"Sales","Credits":2},
{"CourseID":880,"Title":"Product Management","Credits":4},
{"CourseID":881,"Title":"Engineering","Credits":2},
{"CourseID":882,"Title":"Research and Development","Credits":2},
{"CourseID":883,"Title":"Marketing","Credits":2},
{"CourseID":884,"Title":"Accounting","Credits":3},
{"CourseID":885,"Title":"Sales","Credits":3},
{"CourseID":886,"Title":"Services","Credits":4},
{"CourseID":887,"Title":"Engineering","Credits":3},
{"CourseID":888,"Title":"Engineering","Credits":3},
{"CourseID":889,"Title":"Business Development","Credits":5},
{"CourseID":890,"Title":"Services","Credits":4},
{"CourseID":891,"Title":"Support","Credits":3},
{"CourseID":892,"Title":"Human Resources","Credits":2},
{"CourseID":893,"Title":"Services","Credits":3},
{"CourseID":894,"Title":"Product Management","Credits":3},
{"CourseID":895,"Title":"Legal","Credits":3},
{"CourseID":896,"Title":"Legal","Credits":3},
{"CourseID":897,"Title":"Research and Development","Credits":2},
{"CourseID":898,"Title":"Accounting","Credits":3},
{"CourseID":899,"Title":"Human Resources","Credits":1},
{"CourseID":900,"Title":"Sales","Credits":2},
{"CourseID":901,"Title":"Accounting","Credits":2},
{"CourseID":902,"Title":"Business Development","Credits":4},
{"CourseID":903,"Title":"Marketing","Credits":4},
{"CourseID":904,"Title":"Business Development","Credits":1},
{"CourseID":905,"Title":"Accounting","Credits":3},
{"CourseID":906,"Title":"Product Management","Credits":3},
{"CourseID":907,"Title":"Product Management","Credits":1},
{"CourseID":908,"Title":"Accounting","Credits":1},
{"CourseID":909,"Title":"Services","Credits":5},
{"CourseID":910,"Title":"Support","Credits":2},
{"CourseID":911,"Title":"Legal","Credits":4},
{"CourseID":912,"Title":"Legal","Credits":2},
{"CourseID":913,"Title":"Business Development","Credits":1},
{"CourseID":914,"Title":"Services","Credits":1},
{"CourseID":915,"Title":"Training","Credits":2},
{"CourseID":916,"Title":"Sales","Credits":2},
{"CourseID":917,"Title":"Engineering","Credits":4},
{"CourseID":918,"Title":"Services","Credits":4},
{"CourseID":919,"Title":"Business Development","Credits":2},
{"CourseID":920,"Title":"Services","Credits":1},
{"CourseID":921,"Title":"Support","Credits":5},
{"CourseID":922,"Title":"Training","Credits":3},
{"CourseID":923,"Title":"Human Resources","Credits":1},
{"CourseID":924,"Title":"Human Resources","Credits":3},
{"CourseID":925,"Title":"Product Management","Credits":5},
{"CourseID":926,"Title":"Research and Development","Credits":4},
{"CourseID":927,"Title":"Research and Development","Credits":5},
{"CourseID":928,"Title":"Human Resources","Credits":3},
{"CourseID":929,"Title":"Product Management","Credits":4},
{"CourseID":930,"Title":"Sales","Credits":5},
{"CourseID":931,"Title":"Engineering","Credits":1},
{"CourseID":932,"Title":"Legal","Credits":5},
{"CourseID":933,"Title":"Human Resources","Credits":5},
{"CourseID":934,"Title":"Support","Credits":2},
{"CourseID":935,"Title":"Sales","Credits":1},
{"CourseID":936,"Title":"Training","Credits":2},
{"CourseID":937,"Title":"Business Development","Credits":4},
{"CourseID":938,"Title":"Sales","Credits":5},
{"CourseID":939,"Title":"Sales","Credits":3},
{"CourseID":940,"Title":"Services","Credits":4},
{"CourseID":941,"Title":"Business Development","Credits":2},
{"CourseID":942,"Title":"Training","Credits":3},
{"CourseID":943,"Title":"Legal","Credits":4},
{"CourseID":944,"Title":"Engineering","Credits":5},
{"CourseID":945,"Title":"Sales","Credits":1},
{"CourseID":946,"Title":"Engineering","Credits":5},
{"CourseID":947,"Title":"Sales","Credits":3},
{"CourseID":948,"Title":"Accounting","Credits":1},
{"CourseID":949,"Title":"Services","Credits":4},
{"CourseID":950,"Title":"Support","Credits":2},
{"CourseID":951,"Title":"Accounting","Credits":5},
{"CourseID":952,"Title":"Research and Development","Credits":3},
{"CourseID":953,"Title":"Business Development","Credits":3},
{"CourseID":954,"Title":"Business Development","Credits":5},
{"CourseID":955,"Title":"Sales","Credits":1},
{"CourseID":956,"Title":"Product Management","Credits":2},
{"CourseID":957,"Title":"Engineering","Credits":3},
{"CourseID":958,"Title":"Business Development","Credits":2},
{"CourseID":959,"Title":"Research and Development","Credits":4},
{"CourseID":960,"Title":"Engineering","Credits":3},
{"CourseID":961,"Title":"Business Development","Credits":5},
{"CourseID":962,"Title":"Marketing","Credits":5},
{"CourseID":963,"Title":"Business Development","Credits":4},
{"CourseID":964,"Title":"Business Development","Credits":5},
{"CourseID":965,"Title":"Accounting","Credits":2},
{"CourseID":966,"Title":"Sales","Credits":1},
{"CourseID":967,"Title":"Support","Credits":5},
{"CourseID":968,"Title":"Marketing","Credits":2},
{"CourseID":969,"Title":"Accounting","Credits":3},
{"CourseID":970,"Title":"Human Resources","Credits":5},
{"CourseID":971,"Title":"Business Development","Credits":3},
{"CourseID":972,"Title":"Human Resources","Credits":2},
{"CourseID":973,"Title":"Human Resources","Credits":5},
{"CourseID":974,"Title":"Sales","Credits":4},
{"CourseID":975,"Title":"Accounting","Credits":3},
{"CourseID":976,"Title":"Sales","Credits":4},
{"CourseID":977,"Title":"Support","Credits":2},
{"CourseID":978,"Title":"Product Management","Credits":5},
{"CourseID":979,"Title":"Research and Development","Credits":2},
{"CourseID":980,"Title":"Support","Credits":3},
{"CourseID":981,"Title":"Legal","Credits":1},
{"CourseID":982,"Title":"Training","Credits":1},
{"CourseID":983,"Title":"Training","Credits":4},
{"CourseID":984,"Title":"Legal","Credits":5},
{"CourseID":985,"Title":"Research and Development","Credits":5},
{"CourseID":986,"Title":"Accounting","Credits":5},
{"CourseID":987,"Title":"Product Management","Credits":5},
{"CourseID":988,"Title":"Training","Credits":1},
{"CourseID":989,"Title":"Business Development","Credits":4},
{"CourseID":990,"Title":"Services","Credits":2},
{"CourseID":991,"Title":"Engineering","Credits":1},
{"CourseID":992,"Title":"Product Management","Credits":1},
{"CourseID":993,"Title":"Training","Credits":1},
{"CourseID":994,"Title":"Research and Development","Credits":4},
{"CourseID":995,"Title":"Legal","Credits":2},
{"CourseID":996,"Title":"Legal","Credits":4},
{"CourseID":997,"Title":"Business Development","Credits":5},
{"CourseID":998,"Title":"Accounting","Credits":5},
{"CourseID":999,"Title":"Legal","Credits":4},
{"CourseID":1000,"Title":"Human Resources","Credits":5}]